mesh_processing/__init__.py
mesh_processing/logging_config.py
mesh_processing/main.py
mesh_processing/mesh_analysis.py
mesh_processing/mesh_exceptions.py
mesh_processing/mesh_load.py
mesh_processing/mesh_sdf.py
mesh_processing/mesh_simplification.py
mesh_processing/mesh_visualizer.py
mesh_processing/utils.py
jp_mesh-0.1.1.dist-info/LICENSE
jp_mesh-0.1.1.dist-info/METADATA
jp_mesh-0.1.1.dist-info/WHEEL
jp_mesh-0.1.1.dist-info/top_level.txt
jp_mesh-0.1.1.dist-info/RECORD
