Metadata-Version: 2.1
Name: jp_mesh
Version: 0.1.1
Summary: A package for 3D mesh processing and analysis
Home-page: https://github.com/jeevanpillay/jp-mesh
Author: jeevanpillay
Author-email: jp@jeevanpillay.com
Project-URL: Bug Tracker, https://github.com/jeevanpillay/jp-mesh/issues
Project-URL: Documentation, https://github.com/jeevanpillay/jp-mesh/wiki
Keywords: mesh,3D,processing,analysis,simplification,curvature,SDF
Classifier: Development Status :: 3 - Alpha
Classifier: Intended Audience :: Developers
Classifier: License :: OSI Approved :: MIT License
Classifier: Operating System :: OS Independent
Classifier: Programming Language :: Python :: 3
Classifier: Programming Language :: Python :: 3.10
Classifier: Programming Language :: Python :: 3.11
Classifier: Programming Language :: Python :: 3.12
Requires-Python: >=3.10
License-File: LICENSE
Requires-Dist: numpy
Requires-Dist: trimesh
Requires-Dist: pyvista
Requires-Dist: pymeshlab
Requires-Dist: rtree
Requires-Dist: mesh-to-sdf
